elampclient/__init__.py
elampclient/client.py
elampclient/elamprequest.py
elampclient/exceptions.py
elampclient/server.py
elampclient/version.py
elampclient/api_methods/__init__.py
elampclient/api_methods/skills.py
elampclient/api_methods/admin/__init__.py
elampclient/api_methods/admin/application.py
elampclient/api_methods/compose/__init__.py
elampclient/api_methods/compose/libraries.py
elampclient/api_methods/compose/powers.py
elampclient/api_methods/compose/qualifiers.py
elampclient/api_methods/compose/skill_profiles.py
elampclient/api_methods/compose/skills.py
elampclient/api_methods/run/__init__.py
elampclient/api_methods/run/users.py
elampclient/api_methods/search/__init__.py
elampclient/api_methods/search/analytics.py
elampclient/api_methods/search/search.py
elampclient/auth/__init__.py
elampclient/auth/jwt_auth.py
elampclient-1.2.1.dist-info/METADATA
elampclient-1.2.1.dist-info/RECORD
elampclient-1.2.1.dist-info/WHEEL
elampclient-1.2.1.dist-info/top_level.txt
tests/auth/__init__.py
tests/auth/jwt_auth_test.py
