Metadata-Version: 2.1
Name: elampclient
Version: 1.2.1
Summary: eLamp API clients for Web API
Home-page: https://github.com/elampapi/python-elampclient
Author: eLamp
Author-email: support@elamp.fr
License: MIT
Keywords: elamp elamp-web elamp-api skill skill data
Platform: UNKNOWN
Classifier: Development Status :: 5 - Production/Stable
Classifier: Intended Audience :: Developers
Classifier: Topic :: System :: Networking
Classifier: Topic :: Office/Business
Classifier: Programming Language :: Python :: 2
Classifier: Programming Language :: Python :: 2.7
Classifier: Programming Language :: Python :: 3
Classifier: Programming Language :: Python :: 3.3
Classifier: Programming Language :: Python :: 3.4
Classifier: Programming Language :: Python :: 3.5
Classifier: Programming Language :: Python :: 3.6
Requires-Dist: websocket-client (<1.0a0,>=0.35)
Requires-Dist: requests (<3.0a0,>=2.11)
Requires-Dist: six (<2.0a0,>=1.10)
Requires-Dist: PyJWT (>=1.6.4)
Requires-Dist: cryptography (>=2.3)
